CONTRIBUTING.md
MANIFEST.in
README.rst
setup.py
docs/HISTORY.txt
docs/INSTALL.txt
docs/LICENSE.GPL
docs/LICENSE.txt
eea/__init__.py
eea.progressbar.egg-info/PKG-INFO
eea.progressbar.egg-info/SOURCES.txt
eea.progressbar.egg-info/dependency_links.txt
eea.progressbar.egg-info/entry_points.txt
eea.progressbar.egg-info/namespace_packages.txt
eea.progressbar.egg-info/not-zip-safe
eea.progressbar.egg-info/requires.txt
eea.progressbar.egg-info/top_level.txt
eea/progressbar/README.txt
eea/progressbar/__init__.py
eea/progressbar/config.py
eea/progressbar/configure.zcml
eea/progressbar/interfaces.py
eea/progressbar/meta.zcml
eea/progressbar/profiles.zcml
eea/progressbar/setuphandlers.py
eea/progressbar/version.txt
eea/progressbar/Extensions/install.py
eea/progressbar/api/__init__.py
eea/progressbar/api/adapters.py
eea/progressbar/api/configure.zcml
eea/progressbar/browser/__init__.py
eea/progressbar/browser/configure.zcml
eea/progressbar/browser/app/__init__.py
eea/progressbar/browser/app/error.py
eea/progressbar/browser/app/tool.py
eea/progressbar/browser/app/view.py
eea/progressbar/browser/app/viewlet.py
eea/progressbar/browser/css/controlpanel.css
eea/progressbar/browser/css/view.css
eea/progressbar/browser/img/icon.png
eea/progressbar/browser/img/icon.xcf
eea/progressbar/browser/js/controlpanel.js
eea/progressbar/browser/js/view.js
eea/progressbar/browser/zpt/collection-progress.pt
eea/progressbar/browser/zpt/error.pt
eea/progressbar/browser/zpt/metadata.cpanel.pt
eea/progressbar/browser/zpt/metadata.import.pt
eea/progressbar/browser/zpt/metadata.pt
eea/progressbar/browser/zpt/metadata.viewlet.pt
eea/progressbar/browser/zpt/progress.cpanel.pt
eea/progressbar/browser/zpt/progress.pt
eea/progressbar/browser/zpt/progress.viewlet.pt
eea/progressbar/browser/zpt/trail.pt
eea/progressbar/browser/zpt/trail.viewlet.pt
eea/progressbar/content/__init__.py
eea/progressbar/content/configure.zcml
eea/progressbar/content/contenttype.py
eea/progressbar/content/events.py
eea/progressbar/content/interfaces.py
eea/progressbar/content/tool.png
eea/progressbar/content/tool.py
eea/progressbar/controlpanel/__init__.py
eea/progressbar/controlpanel/configure.zcml
eea/progressbar/controlpanel/interfaces.py
eea/progressbar/controlpanel/settings.py
eea/progressbar/docs/exportimport.txt
